omesa/__init__.py
omesa/data.py
omesa/experiment.py
omesa/featurizer.py
omesa/logger.py
omesa/pipes.py
omesa/processor.py
omesa-0.2.9a0.dist-info/DESCRIPTION.rst
omesa-0.2.9a0.dist-info/METADATA
omesa-0.2.9a0.dist-info/RECORD
omesa-0.2.9a0.dist-info/WHEEL
omesa-0.2.9a0.dist-info/metadata.json
omesa-0.2.9a0.dist-info/top_level.txt
omesa-0.2.9a0.dist-info/zip-safe
