Metadata-Version: 2.0
Name: omesa
Version: 0.2.9a0
Summary: A small framework for reproducible text mining research
Home-page: https://github.com/cmry/shed
Author: Chris Emmery
Author-email: chris.emmery@uantwerpen.be
License: MIT
Platform: UNKNOWN
Requires-Dist: scikit-learn (>=0.17)
